[
  {
    "chinese_name": "阿根廷约翰·肯尼迪大学",
    "english_name": "Universidad Argentina John F. Kennedy"
  },
  {
    "chinese_name": "阿根廷天主教大学",
    "english_name": "Pontificia Universidad Católica Argentina Santa María de los Buenos Aires"
  },
  {
    "chinese_name": "阿根廷企业大学",
    "english_name": "Universidad Argentina de la Empresa"
  },
  {
    "chinese_name": "布宜诺斯艾利斯大学",
    "english_name": "Universidad de Buenos Aires"
  },
  {
    "chinese_name": "布宜诺斯艾利斯精神分析协会心理健康大学学院",
    "english_name": "Instituto Universitario de Salud Mental de la Asociación Psicoanalítica de Buenos Aires"
  },
  {
    "chinese_name": "贝尔格拉诺大学",
    "english_name": "Universidad de Belgrano"
  },
  {
    "chinese_name": "巴勒莫大学",
    "english_name": "Universidad de Palermo"
  },
  {
    "chinese_name": "CEMA大学",
    "english_name": "Universidad del CEMA"
  },
  {
    "chinese_name": "21世纪企业大学",
    "english_name": "Universidad Empresarial Siglo 21"
  },
  {
    "chinese_name": "二月三日国立大学",
    "english_name": "Universidad Nacional de Tres de Febrero"
  },
  {
    "chinese_name": "国立技术大学",
    "english_name": "Universidad Tecnológica Nacional"
  },
  {
    "chinese_name": "汉西翻译专科学校",
    "english_name": "Instituto Superior de Intérpretes de Idioma Chino"
  },
  {
    "chinese_name": "海事商务大学",
    "english_name": "Universidad de la Marina Mercante"
  },
  {
    "chinese_name": "科尔多瓦国立大学",
    "english_name": "Universidad Nacional de Córdoba"
  },
  {
    "chinese_name": "科尔多瓦天主教大学",
    "english_name": "Universidad Católica de Córdoba"
  },
  {
    "chinese_name": "拉里奥哈国立大学",
    "english_name": "Universidad Nacional de La Rioja"
  },
  {
    "chinese_name": "拉丁美洲社会科学院（FLACSO）",
    "english_name": "Facultad Latinoamericana de Ciencias Sociales (FLACSO)"
  },
  {
    "chinese_name": "拉努斯国立大学",
    "english_name": "Universidad Nacional de Lanús"
  },
  {
    "chinese_name": "洛马斯德萨莫拉国立大学",
    "english_name": "Universidad Nacional de Lomas de Zamora"
  },
  {
    "chinese_name": "罗萨里奥国立大学",
    "english_name": "Universidad Nacional de Rosario"
  },
  {
    "chinese_name": "迈蒙尼德大学",
    "english_name": "Universidad Maimónides"
  },
  {
    "chinese_name": "美洲开放大学",
    "english_name": "Universidad Abierta Interamericana"
  },
  {
    "chinese_name": "南部国立大学",
    "english_name": "Universidad Nacional del Sur"
  },
  {
    "chinese_name": "南方大学",
    "english_name": "Universidad Austral"
  },
  {
    "chinese_name": "企业与社会科学大学",
    "english_name": "Universidad de Ciencias Empresariales y Sociales"
  },
  {
    "chinese_name": "圣安德烈斯大学",
    "english_name": "Universidad de San Andrés"
  },
  {
    "chinese_name": "萨尔瓦多大学",
    "english_name": "Universidad del Salvador"
  },
  {
    "chinese_name": "托尔夸托•迪特拉大学",
    "english_name": "Universidad Torcuato Di Tella"
  }
]